hapi_nn/__init__.py
hapi_nn/config.py
hapi_nn/testing.py
hapi_nn/training.py
hapi_nn/util.py
hapi_nn-0.1.0.dist-info/LICENSE
hapi_nn-0.1.0.dist-info/METADATA
hapi_nn-0.1.0.dist-info/WHEEL
hapi_nn-0.1.0.dist-info/top_level.txt
hapi_nn-0.1.0.dist-info/RECORD
