Metadata-Version: 2.1
Name: hapi-nn
Version: 0.1.0
Summary: HAPI-NN allows interfacing of HAPI with TensorFlow and PyTorch to rapidly create deep neural network models for predicting and forecasting.
Home-page: https://github.com/hapi-server/application-neuralnetwork-python
Author: Travis Hammond
Author-email: Travis.Hammond@jhuapl.edu
License: LICENSE
Classifier: Programming Language :: Python :: 3
Classifier: Topic :: Scientific/Engineering
License-File: LICENSE
Requires-Dist: numpy (>=1.22)
Requires-Dist: matplotlib (>=3.4)
Requires-Dist: hapiclient (>=0.2)
